{"airship":{"bgm":{"name":"SMG2 The Starship Travels","pan":0,"pitch":100,"volume":100},"characterIndex":3,"characterName":"Vehicle","startMapId":0,"startX":0,"startY":0},"armorTypes":["","一般裝備","魔法裝備","輕裝備","重裝甲","共通","主角專用","苦力喵專用","國泰專用","雷歐專用","副手-斧","副手-劍","副手-槍","無法拆卸的專用裝備"],"attackMotions":[{"type":0,"weaponImageId":0},{"type":1,"weaponImageId":4},{"type":0,"weaponImageId":12},{"type":1,"weaponImageId":2},{"type":1,"weaponImageId":6},{"type":1,"weaponImageId":2},{"type":2,"weaponImageId":7},{"type":1,"weaponImageId":2},{"type":1,"weaponImageId":6},{"type":1,"weaponImageId":2},{"type":1,"weaponImageId":6},{"type":2,"weaponImageId":25},{"type":1,"weaponImageId":2},{"type":1,"weaponImageId":2},{"type":2,"weaponImageId":25},{"type":0,"weaponImageId":12},{"type":1,"weaponImageId":2},{"type":1,"weaponImageId":2},{"type":1,"weaponImageId":2}],"battleBgm":{"name":"Battle1","pan":0,"pitch":100,"volume":100},"battleBack1Name":"Castle","battleBack2Name":"Castle1","battlerHue":0,"battlerName":"步行圖","boat":{"bgm":{"name":"Ship","pan":0,"pitch":100,"volume":100},"characterIndex":0,"characterName":"Vehicle","startMapId":0,"startX":0,"startY":0},"currencyUnit":"金幣","defeatMe":{"name":"汙點","pan":0,"pitch":100,"volume":90},"editMapId":46,"elements":["","物理","吸收","火","冰","雷","水","地","風","光","闇","肛","無","超必殺","","破甲","肥皂","對男女生","日光","","","","","","",""],"equipTypes":["","主手","副手","頭部","身體","飾品","特性1","特性2"],"gameTitle":"奇葩大冒險2 亞空異變","gameoverMe":{"name":"Game Over","pan":0,"pitch":100,"volume":100},"locale":"zh_TW","magicSkills":[5,2,6,7,8,9,10,11,12],"menuCommands":[true,true,true,true,true,false],"optDisplayTp":true,"optDrawTitle":true,"optExtraExp":false,"optFloorDeath":true,"optFollowers":false,"optSideView":true,"optSlipDeath":false,"optTransparent":false,"partyMembers":[],"ship":{"bgm":{"name":"Ship","pan":0,"pitch":100,"volume":100},"characterIndex":1,"characterName":"Vehicle","startMapId":2,"startX":19,"startY":35},"skillTypes":["","特殊技能","魔法技能","劍技","槍術","杖魔法","火書","水書","風書","地書","雷書","光書","闇書","演奏","招式","","","","","",""],"sounds":[{"name":"Cursor2","pan":0,"pitch":100,"volume":80},{"name":"Decision3","pan":0,"pitch":100,"volume":80},{"name":"Cancel2","pan":0,"pitch":100,"volume":80},{"name":"Buzzer1","pan":0,"pitch":100,"volume":80},{"name":"Equip1","pan":0,"pitch":100,"volume":80},{"name":"基基","pan":0,"pitch":100,"volume":90},{"name":"スタート","pan":0,"pitch":100,"volume":100},{"name":"這時候要進行激戰","pan":0,"pitch":100,"volume":100},{"name":"高超走位","pan":0,"pitch":100,"volume":100},{"name":"Attack3","pan":0,"pitch":100,"volume":80},{"name":"看來一點屁用都沒有","pan":0,"pitch":100,"volume":100},{"name":"我成功打贏我超強","pan":0,"pitch":100,"volume":100},{"name":"我成功打贏我超強","pan":0,"pitch":100,"volume":100},{"name":"Collapse4","pan":0,"pitch":100,"volume":80},{"name":"Damage2","pan":0,"pitch":100,"volume":100},{"name":"Collapse2","pan":0,"pitch":100,"volume":100},{"name":"Recovery","pan":0,"pitch":100,"volume":100},{"name":"迴避了","pan":0,"pitch":100,"volume":100},{"name":"超猛","pan":0,"pitch":100,"volume":100},{"name":"迴避了","pan":0,"pitch":100,"volume":100},{"name":"Reflection","pan":0,"pitch":100,"volume":80},{"name":"Shop","pan":0,"pitch":100,"volume":80},{"name":"Item3","pan":0,"pitch":100,"volume":80},{"name":"Skill2","pan":0,"pitch":100,"volume":100}],"startMapId":1,"startX":8,"startY":6,"switches":["","測試模式","不可能打開","可以輸入指令","指令輸入中","解鎖問答 1-1","解鎖問答 1-2","解鎖問答 1-3","解鎖問答 1-4","解鎖問答 2-1","解鎖問答 2-2","解鎖問答 2-3","解鎖問答 2-4","解鎖問答 2-5","解鎖問答 2-6","解鎖問答 2-7","解鎖問答 2-8","利歐打招呼","你屎惹","全體停止","3-無色通關","租借釣竿","釣魚中","搶走釣竿","初入亞空城","選擇對戰對手","自由模式-選擇地圖","自由模式-降落","自由模式-彈出地圖名","自由模式-禁止使用地圖","大中天(強)在隊伍中","看領隊技能模式","暫時關閉選關取消功能","播放進場動畫","村莊-已食用餐點","結婚 砸向開關","夜","ST1-對話過苦力喵","資料庫-圖像運作","正在邀請用餐","1-無色通關","第一次進入無色世界","傢具放置模式","傢具放置模式2","傢具移動模式","傢具刪除模式","無色-開始移動","無色-停止","2-無色通關","選擇訓練對象","探險隊-屬性一致判定","探險隊1-屬性一致加成","探險隊2-屬性一致加成","探險隊3-屬性一致加成","探險隊4-屬性一致加成","探險隊5-屬性一致加成","選擇完訓練對象","自由見過C男","自由見過小丑","自由進入利歐堡壘","自由-在水下","初次見面乖狗乖","血淚王國-解除封鎖","血淚王國-解除封鎖-全","血淚王國-初見登山道","初見哞晤","初見尤莉亞","獲得降低難度","啟動降低難度","降低難度首次免費","4-無色通關","SRPG Battle","SRPG_BattleSkip","SRPG_MapBattle","自宅BGM 選擇音調","取得鍵刃","5-無色通關","跳過戰役","啟動千變萬化","厄咒解放","6-無色通關","ST6啟動支援","表裡通道封鎖","裏 地之遺跡開鎖","裏 船抵達","裏 船往","裏 水之遺跡開鎖","裏 雷之遺跡開鎖","裏 火之遺跡開鎖","再見尤莉亞","正在查看同伴故事","7-無色通關","ST7-3 編組返回用","取得雷龍石","初見菲娜","開啟友情奇蹟","關卡中見過艾薇","ST3 吸收隱龍魂","ST5 嘗試搶奪浴炎花","自由 利亞露村莊事件","自由 利亞露村莊事件2","亞空城關卡用1","亞空城關卡用2","亞空城關卡用3","亞空城關卡用4","亞空城關卡用5","亞空城關卡用6","亞空城關卡用7","亞空城關卡用8","亞空城關卡用9","亞空城關卡用10","亞空城關卡用11","亞空城關卡用12","亞空城關卡用13","亞空城關卡用14","亞空城關卡用15","亞空城關卡用16","亞空城關卡用17","亞空城關卡用18","亞空城關卡用19","亞空城關卡用20","亞空城關卡用21","亞空城關卡用22","亞空城關卡用23","亞空城關卡用24","亞空城關卡用25","亞空城關卡用26","亞空城關卡用27","亞空城關卡用28","亞空城關卡用29","亞空城關卡用30","亞空城關卡用31","亞空城關卡用32","亞空城關卡用33","亞空城關卡用34","亞空城關卡用35","亞空城關卡用36","亞空城關卡用37","亞空城關卡用38","亞空城關卡用39","亞空城關卡用40","","","","","","","","","","","解鎖角色-主角","解鎖角色-利歐","解鎖角色-大中天","解鎖角色-苦力喵","解鎖角色-國泰","解鎖角色-修伊","解鎖角色-愛莉絲","解鎖角色-雷歐","解鎖角色-狩矢","解鎖角色-利優","解鎖角色-洛伊","解鎖角色-望","解鎖角色-斯利茲","解鎖角色-殘楓","解鎖角色-祈","解鎖角色-利牙","","","","","","","","","","解鎖角色-蒼樹","解鎖角色-創也","解鎖角色-龍","解鎖角色-雷沃夫","解鎖角色-剎那","解鎖角色-凱因","解鎖角色-布雷德","解鎖角色-基拉姆德","解鎖角色-圖涅勒","解鎖角色-禍","解鎖角色-鵂","解鎖角色-謝爾","","","","","","","","","","","","","","1-6通關","2-6通關","3-6通關","4-6通關","5-6通關","6-6通關","7-6通關","禁止用特殊道具","","","","","","","","","","","","","","","","","","","","","","","","","","","","","","","","","","","","","","","","","","","","","","","","","","","","","","","","","","","","","","","","","","","","","","","","","","","","","","","","","","","","","","","","","","","","","","","","","","","","","","","","","","","","","","","","","","","","","","","","","","","","","","","","","","","","","","","","","","","","","","","解鎖探險地點1","解鎖探險地點2","解鎖探險地點3","解鎖探險地點4","解鎖探險地點5","解鎖探險地點6","解鎖探險地點7","解鎖探險地點8","解鎖探險地點9","解鎖探險地點10","解鎖探險地點11","解鎖探險地點12","解鎖探險地點13","解鎖探險地點14","解鎖探險地點15","解鎖探險地點16","解鎖探險地點17","解鎖探險地點18","解鎖探險地點19","解鎖探險地點20","解鎖探險地點21","解鎖探險地點22","解鎖探險地點23","解鎖探險地點24","解鎖探險地點25","解鎖探險地點26","解鎖探險地點27","解鎖探險地點28","解鎖探險地點29","解鎖探險地點30","解鎖探險地點31","解鎖探險地點32","解鎖探險地點33","解鎖探險地點34","解鎖探險地點35","解鎖探險地點36","解鎖探險地點37","解鎖探險地點38","解鎖探險地點39","解鎖探險地點40","解鎖探險地點41","解鎖探險地點42","解鎖探險地點43","解鎖探險地點44","解鎖探險地點45","解鎖探險地點46","解鎖探險地點47","解鎖探險地點48","解鎖探險地點49","解鎖探險地點50","解鎖探險隊1","解鎖探險隊2","解鎖探險隊3","解鎖探險隊4","解鎖探險隊5","解鎖探險隊6","解鎖探險隊7","解鎖探險隊8","解鎖探險隊9","解鎖探險隊10","解鎖探險隊11","解鎖探險隊12","解鎖探險隊13","解鎖探險隊14","解鎖探險隊15","解鎖探險隊16","解鎖探險隊17","解鎖探險隊18","解鎖探險隊19","解鎖探險隊20","解鎖探險隊21","解鎖探險隊22","解鎖探險隊23","解鎖探險隊24","解鎖探險隊25","解鎖探險隊26","解鎖探險隊27","解鎖探險隊28","解鎖探險隊29","解鎖探險隊30","解鎖探險隊31","解鎖探險隊32","解鎖探險隊33","解鎖探險隊34","解鎖探險隊35","解鎖探險隊36","解鎖探險隊37","解鎖探險隊38","解鎖探險隊39","解鎖探險隊40","解鎖探險隊41","解鎖探險隊42","解鎖探險隊43","解鎖探險隊44","解鎖探險隊45","解鎖探險隊46","解鎖探險隊47","解鎖探險隊48","解鎖探險隊49","解鎖探險隊50","自由-解鎖地點1","自由-解鎖地點2","自由-解鎖地點3","自由-解鎖地點4","自由-解鎖地點5","自由-解鎖地點6","自由-解鎖地點7","自由-解鎖地點8","自由-解鎖地點9","自由-解鎖地點10","自由-解鎖地點11","自由-解鎖地點12","自由-解鎖地點13","自由-解鎖地點14","自由-解鎖地點15","自由-解鎖地點16","自由-解鎖地點17","自由-解鎖地點18","自由-解鎖地點19","自由-解鎖地點20","自由-解鎖地點21","自由-解鎖地點22","自由-解鎖地點23","自由-解鎖地點24","自由-解鎖地點25","自由-解鎖地點26","自由-解鎖地點27","自由-解鎖地點28","自由-解鎖地點29","自由-解鎖地點30","自由-解鎖地點31","自由-解鎖地點32","自由-解鎖地點33","自由-解鎖地點34","自由-解鎖地點35","自由-解鎖地點36","自由-解鎖地點37","自由-解鎖地點38","自由-解鎖地點39","自由-解鎖地點40","自由-解鎖地點41","自由-解鎖地點42","自由-解鎖地點43","自由-解鎖地點44","自由-解鎖地點45","自由-解鎖地點46","自由-解鎖地點47","自由-解鎖地點48","自由-解鎖地點49","自由-解鎖地點50","羈絆度 主角-利歐","羈絆度 主角-大中天","羈絆度 主角-苦力喵","羈絆度 主角-國泰","羈絆度 主角-修伊","羈絆度 主角-愛莉絲","羈絆度 利歐-大中天","羈絆度 利歐-苦力喵","羈絆度 利歐-國泰","羈絆度 利歐-修伊","羈絆度 利歐-愛莉絲","羈絆度 大中天-苦力喵","羈絆度 大中天-國泰","羈絆度 大中天-修伊","羈絆度 大中天-愛莉絲","羈絆度 苦力喵-國泰","羈絆度 苦力喵-修伊","羈絆度 苦力喵-愛莉絲","羈絆度 國泰-修伊","羈絆度 國泰-愛莉絲","羈絆度 修伊-愛莉絲","羈絆度 主角-雷歐","羈絆度 利歐-雷歐","羈絆度 大中天-雷歐","羈絆度 苦力喵-雷歐","羈絆度 國泰-雷歐","羈絆度 修伊-雷歐","羈絆度 愛莉絲-雷歐","羈絆度 主角-狩矢","羈絆度 利歐-狩矢","羈絆度 大中天-狩矢","羈絆度 苦力喵-狩矢","羈絆度 國泰-狩矢","羈絆度 修伊-狩矢","羈絆度 愛莉絲-狩矢","羈絆度 雷歐-狩矢","羈絆度 主角-利優","羈絆度 利歐-利優","羈絆度 大中天-利優","羈絆度 苦力喵-利優","羈絆度 國泰-利優","羈絆度 修伊-利優","羈絆度 愛莉絲-利優","羈絆度 雷歐-利優","羈絆度 狩矢-利優","羈絆度 主角-洛伊","羈絆度 利歐-洛伊","羈絆度 大中天-洛伊","羈絆度 苦力喵-洛伊","羈絆度 國泰-洛伊","羈絆度 修伊-洛伊","羈絆度 愛莉絲-洛伊","羈絆度 雷歐-洛伊","羈絆度 狩矢-洛伊","羈絆度 利優-洛伊","羈絆度 主角-望","羈絆度 利歐-望","羈絆度 大中天-望","羈絆度 苦力喵-望","羈絆度 國泰-望","羈絆度 修伊-望","羈絆度 愛莉絲-望","羈絆度 雷歐-望","羈絆度 狩矢-望","羈絆度 利優-望","羈絆度 洛伊-望","羈絆度 主角-斯利茲","羈絆度 利歐-斯利茲","羈絆度 大中天-斯利茲","羈絆度 苦力喵-斯利茲","羈絆度 國泰-斯利茲","羈絆度 修伊-斯利茲","羈絆度 愛莉絲-斯利茲","羈絆度 雷歐-斯利茲","羈絆度 狩矢-斯利茲","羈絆度 利優-斯利茲","羈絆度 洛伊-斯利茲","羈絆度 望-斯利茲","羈絆度 主角-殘楓","羈絆度 利歐-殘楓","羈絆度 大中天-殘楓","羈絆度 苦力喵-殘楓","羈絆度 國泰-殘楓","羈絆度 修伊-殘楓","羈絆度 愛莉絲-殘楓","羈絆度 雷歐-殘楓","羈絆度 狩矢-殘楓","羈絆度 利優-殘楓","羈絆度 洛伊-殘楓","羈絆度 望-殘楓","羈絆度 斯利茲-殘楓","羈絆度 主角-祈","羈絆度 利歐-祈","羈絆度 大中天-祈","羈絆度 苦力喵-祈","羈絆度 國泰-祈","羈絆度 修伊-祈","羈絆度 愛莉絲-祈","羈絆度 雷歐-祈","羈絆度 狩矢-祈","羈絆度 利優-祈","羈絆度 洛伊-祈","羈絆度 望-祈","羈絆度 斯利茲-祈","羈絆度 殘楓-祈","羈絆度 主角-利牙","羈絆度 利歐-利牙","羈絆度 大中天-利牙","羈絆度 苦力喵-利牙","羈絆度 國泰-利牙","羈絆度 修伊-利牙","羈絆度 愛莉絲-利牙","羈絆度 雷歐-利牙","羈絆度 狩矢-利牙","羈絆度 利優-利牙","羈絆度 洛伊-利牙","羈絆度 望-利牙","羈絆度 斯利茲-利牙","羈絆度 殘楓-利牙","羈絆度 祈-利牙","","","","","","","","","","","","","","","","","","","","","","","","","","","","","","","","","","","","","","","","","","","","","","","","","","","","","","","","","","","","","","","","","","","","","","","","","","","","","","","","","","","","","","","","","","","","","","","","","","","","","","","","","","","","","","","","","","","","","","","","","","","","","","","","","","","","","","","","","","","","","","","","","","","","","","","","","","","","","","","","","","","","","","","","","","","","","","","","","","","","","","","","","","","","","","","","","","","","","","","","","","","","","","","","","","","","","","","","","","","","","","","","","","","","","","","","","","","","","","","","","","","","","","","","","","","","","","","","","","","","","","","","","","","","","","","","","","","","","","","","","","","","","","","","","","","","","","","","","","","","","","","","","","","","","","","","","","","","","","","","","","","","","","","","","","","","","","","","","","","","","","","","","","","","","","","","","","","","","","","","","","","","","","","","","","","","","","","","","","","","","羈絆度 主角-利歐","羈絆度 主角-大中天","羈絆度 主角-苦力喵","羈絆度 主角-國泰","羈絆度 主角-修伊","羈絆度 主角-愛莉絲","羈絆度 利歐-大中天","羈絆度 利歐-苦力喵","羈絆度 利歐-國泰","羈絆度 利歐-修伊","羈絆度 利歐-愛莉絲","羈絆度 大中天-苦力喵","羈絆度 大中天-國泰","羈絆度 大中天-修伊","羈絆度 大中天-愛莉絲","羈絆度 苦力喵-國泰","羈絆度 苦力喵-修伊","羈絆度 苦力喵-愛莉絲","羈絆度 國泰-修伊","羈絆度 國泰-愛莉絲","羈絆度 修伊-愛莉絲","羈絆度 主角-雷歐","羈絆度 利歐-雷歐","羈絆度 大中天-雷歐","羈絆度 苦力喵-雷歐","羈絆度 國泰-雷歐","羈絆度 修伊-雷歐","羈絆度 愛莉絲-雷歐","羈絆度 主角-狩矢","羈絆度 利歐-狩矢","羈絆度 大中天-狩矢","羈絆度 苦力喵-狩矢","羈絆度 國泰-狩矢","羈絆度 修伊-狩矢","羈絆度 愛莉絲-狩矢","羈絆度 雷歐-狩矢","羈絆度 主角-利優","羈絆度 利歐-利優","羈絆度 大中天-利優","羈絆度 苦力喵-利優","羈絆度 國泰-利優","羈絆度 修伊-利優","羈絆度 愛莉絲-利優","羈絆度 雷歐-利優","羈絆度 妮娜-利優","羈絆度 主角-洛伊","羈絆度 利歐-洛伊 ","羈絆度 大中天-洛伊 ","羈絆度 苦力喵-洛伊 ","羈絆度 國泰-洛伊 ","羈絆度 修伊-洛伊 ","羈絆度 愛莉絲-洛伊 ","羈絆度 雷歐-洛伊 ","羈絆度 狩矢-洛伊 ","羈絆度 利優-洛伊 ","羈絆度 主角-望 ","羈絆度 利歐-望 ","羈絆度 大中天-望 ","羈絆度 苦力喵-望 ","羈絆度 國泰-望 ","羈絆度 修伊-望 ","羈絆度 愛莉絲-望 ","羈絆度 雷歐-望 ","羈絆度 狩矢-望 ","羈絆度 利優-望 ","羈絆度 洛伊-望 ","羈絆度 主角-斯利茲 ","羈絆度 利歐-斯利茲","羈絆度 大中天-斯利茲","羈絆度 苦力喵-斯利茲","羈絆度 國泰-斯利茲","羈絆度 修伊-斯利茲","羈絆度 愛莉絲-斯利茲","羈絆度 雷歐-斯利茲","羈絆度 狩矢-斯利茲","羈絆度 利優-斯利茲","羈絆度 洛伊-斯利茲","羈絆度 望-斯利茲","羈絆度 主角-殘楓","羈絆度 利歐-殘楓","羈絆度 大中天-殘楓","羈絆度 苦力喵-殘楓","羈絆度 國泰-殘楓","羈絆度 修伊-殘楓","羈絆度 愛莉絲-殘楓","羈絆度 雷歐-殘楓","羈絆度 狩矢-殘楓","羈絆度 利優-殘楓","羈絆度 洛伊-殘楓","羈絆度 望-殘楓","羈絆度 斯利茲-殘楓","羈絆度 主角-祈","羈絆度 利歐-祈","羈絆度 大中天-祈","羈絆度 苦力喵-祈","羈絆度 國泰-祈","羈絆度 修伊-祈","羈絆度 愛莉絲-祈","羈絆度 雷歐-祈","羈絆度 狩矢-祈","羈絆度 利優-祈","羈絆度 洛伊-祈","羈絆度 望-祈","羈絆度 斯利茲-祈","羈絆度 殘楓-祈","羈絆度 主角-利牙","羈絆度 利歐-利牙","羈絆度 大中天-利牙","羈絆度 苦力喵-利牙","羈絆度 國泰-利牙","羈絆度 修伊-利牙","羈絆度 愛莉絲-利牙","羈絆度 雷歐-利牙","羈絆度 狩矢-利牙","羈絆度 利優-利牙","羈絆度 洛伊-利牙","羈絆度 望-利牙","羈絆度 斯利茲-利牙","羈絆度 殘楓-利牙","羈絆度 祈-利牙","","","","","","","","","","","","","","","","","","","","","","","","","","","","","","","","","","","","","","","","","","","","","","","","","","","","","","","","","","","","","","","","","","","","","","","","","","","","","","","","","","","","","","","","","","","","","","","","","","","","","","","","","","","","","","","","","","","","","","","","","","","","","","","","","","","","","","","","","","","","","","","","","","","","","","","","","","","","","","","","","","","","","","","","","","","","","","","","","","","","","","","","","","","","","","","","","","","","","","","","","","","","","","","","","","","","","","","","","","","","","","","","","","","","","","","","","","","","","","","","","","","","","","","","","","","","","","","","","","","","","","","","","","","","","","","","","","","","","","","","","","","","","","","","","","","","","","","","","","","","","","","","","","","","","","","","","","","","","","","","","","","","","","","","","","","","","","","","","","","","","","","","","","","","","","","","","","","","","","","","","","","","","","","","","","","","","","","","","","","","","羈絆度 主角-利歐","羈絆度 主角-大中天","羈絆度 主角-苦力喵","羈絆度 主角-國泰","羈絆度 主角-修伊","羈絆度 主角-愛莉絲","羈絆度 利歐-大中天","羈絆度 利歐-苦力喵","羈絆度 利歐-國泰","羈絆度 利歐-修伊","羈絆度 利歐-愛莉絲","羈絆度 大中天-苦力喵","羈絆度 大中天-國泰","羈絆度 大中天-修伊","羈絆度 大中天-愛莉絲","羈絆度 苦力喵-國泰","羈絆度 苦力喵-修伊","羈絆度 苦力喵-愛莉絲","羈絆度 國泰-修伊","羈絆度 國泰-愛莉絲","羈絆度 修伊-愛莉絲","羈絆度 主角-雷歐","羈絆度 利歐-雷歐","羈絆度 大中天-雷歐","羈絆度 苦力喵-雷歐","羈絆度 國泰-雷歐","羈絆度 修伊-雷歐","羈絆度 愛莉絲-雷歐","羈絆度 主角-狩矢","羈絆度 利歐-狩矢","羈絆度 大中天-狩矢","羈絆度 苦力喵-狩矢","羈絆度 國泰-狩矢","羈絆度 修伊-狩矢","羈絆度 愛莉絲-狩矢","羈絆度 雷歐-狩矢","羈絆度 主角-利優","羈絆度 利歐-利優","羈絆度 大中天-利優","羈絆度 苦力喵-利優","羈絆度 國泰-利優","羈絆度 修伊-利優","羈絆度 愛莉絲-利優","羈絆度 雷歐-利優","羈絆度 狩矢-利優","羈絆度 主角-洛伊 ","羈絆度 利歐-洛伊 ","羈絆度 大中天-洛伊 ","羈絆度 苦力喵-洛伊 ","羈絆度 國泰-洛伊 ","羈絆度 修伊-洛伊 ","羈絆度 愛莉絲-洛伊 ","羈絆度 雷歐-洛伊 ","羈絆度 狩矢-洛伊 ","羈絆度 利優-洛伊 ","羈絆度 主角-望 ","羈絆度 利歐-望 ","羈絆度 大中天-望 ","羈絆度 苦力喵-望 ","羈絆度 國泰-望 ","羈絆度 修伊-望 ","羈絆度 愛莉絲-望 ","羈絆度 雷歐-望 ","羈絆度 狩矢-望 ","羈絆度 利優-望 ","羈絆度 洛伊-望 ","羈絆度 主角-斯利茲 ","羈絆度 利歐-斯利茲","羈絆度 大中天-斯利茲","羈絆度 苦力喵-斯利茲","羈絆度 國泰-斯利茲","羈絆度 修伊-斯利茲","羈絆度 愛莉絲-斯利茲","羈絆度 雷歐-斯利茲","羈絆度 狩矢-斯利茲","羈絆度 利優-斯利茲","羈絆度 洛伊-斯利茲","羈絆度 望-斯利茲","羈絆度 主角-殘楓","羈絆度 利歐-殘楓","羈絆度 大中天-殘楓","羈絆度 苦力喵-殘楓","羈絆度 國泰-殘楓","羈絆度 修伊-殘楓","羈絆度 愛莉絲-殘楓","羈絆度 雷歐-殘楓","羈絆度 狩矢-殘楓","羈絆度 利優-殘楓","羈絆度 洛伊-殘楓","羈絆度 望-殘楓","羈絆度 斯利茲-殘楓","羈絆度 主角-祈","羈絆度 利歐-祈","羈絆度 大中天-祈","羈絆度 苦力喵-祈","羈絆度 國泰-祈","羈絆度 修伊-祈","羈絆度 愛莉絲-祈","羈絆度 雷歐-祈","羈絆度 狩矢-祈","羈絆度 利優-祈","羈絆度 洛伊-祈","羈絆度 望-祈","羈絆度 斯利茲-祈","羈絆度 殘楓-祈","羈絆度 主角-利牙","羈絆度 利歐-利牙","羈絆度 大中天-利牙","羈絆度 苦力喵-利牙","羈絆度 國泰-利牙","羈絆度 修伊-利牙","羈絆度 愛莉絲-利牙","羈絆度 雷歐-利牙","羈絆度 狩矢-利牙","羈絆度 利優-利牙","羈絆度 洛伊-利牙","羈絆度 望-利牙","羈絆度 斯利茲-利牙","羈絆度 殘楓-利牙","羈絆度 祈-利牙","","","","","","","","","","","","","","","","","","","","","","","","","","","","","","","","","","","","","","","","","","","","","","","","","","","","","","","","","","","","","","","","","","","","","","","","","","","","","","","","","","","","","","","","","","","","","","","","","","","","","","","","","","","","","","","","","","","","","","","","","","","","","","","","","","","","","","","","","","","","","","","","","","","","","","","","","","","","","","","","","","","","","","","","","","","","","","","","","","","","","","","","","","","","","","","","","","","","","","","","","","","","","","","","","","","","","","","","","","","","","","","","","","","","","","","","","","","","","","","","","","","","","","","","","","","","","","","","","","","","","","","","","","","","","","","","","","","","","","","","","","","","","","","","","","","","","","","","","","","","","","","","","","","","","","","","","","","","","","","","","","","","","","","","","","","","","","","","","","","","","","","","","","","","","","","","","","","","","","","","","","","","","","","","","","","","","","","","","","","","","解鎖資料-主角","解鎖資料-利歐","解鎖資料-大中天","解鎖資料-苦力喵","解鎖資料-國泰","解鎖資料-利牙","解鎖資料-GTA-487","解鎖資料-修伊","解鎖資料-愛莉絲","解鎖資料-雷歐","解鎖資料-狩矢","解鎖資料-羅格","解鎖資料-菲莉","解鎖資料-利優","解鎖資料-克羅伊","解鎖資料-瑪爾克斯","解鎖資料-洛伊","解鎖資料-望","解鎖資料-斯利茲","解鎖資料-德爾特","解鎖資料-【禍鎧】","解鎖資料-古拉帝翁","解鎖資料-迪安","解鎖資料-琪雅拉","解鎖資料-傑斯","解鎖資料-殘楓","解鎖資料-塃牙","解鎖資料-澪牙","解鎖資料-珞牙","解鎖資料-颿牙","解鎖資料-熾牙","解鎖資料-閻牙","解鎖資料-葬牙","解鎖資料-尤莉亞","解鎖資料-魄伊德","解鎖資料-祈","解鎖資料-梅克","解鎖資料-光","解鎖資料-艾薇","解鎖資料-龍","解鎖資料-禍","解鎖資料-菲娜","解鎖資料-菲恩圖斯","解鎖資料-鵂","解鎖資料-那伊特","","","","","","","","","","","","","","","","","","","","","","","","","","","","","","","","","","","","","","","","","","","","","","","","","","","","","","","","解鎖資料-亞空城","解鎖資料-主世界","解鎖資料-地之間","解鎖資料-水之間","解鎖資料-雷之間","解鎖資料-風之間","解鎖資料-火之間","解鎖資料-闇之間","解鎖資料-光之間","解鎖資料-裏亞空城","解鎖資料-裏地之間","解鎖資料-裏水之間","解鎖資料-裏雷之間","解鎖資料-裏風之間","解鎖資料-裏火之間","解鎖資料-裏闇之間","解鎖資料-裏光之間","","","","","","","","","","","","","","","","","","","","","","","","","","","","","","","","","","","","","","","","","","","","","","","","","","","","","","","","","","","","","","","","","","","","","","","","","","","","","","","","","","","","解鎖BGM-001","解鎖BGM-002","解鎖BGM-003","解鎖BGM-004","解鎖BGM-005","解鎖BGM-006","解鎖BGM-007","解鎖BGM-008","解鎖BGM-009","解鎖BGM-010","解鎖BGM-011","解鎖BGM-012","解鎖BGM-013","解鎖BGM-014","解鎖BGM-015","解鎖BGM-016","解鎖BGM-017","解鎖BGM-018","解鎖BGM-019","解鎖BGM-020","解鎖BGM-021","解鎖BGM-022","解鎖BGM-023","解鎖BGM-024","解鎖BGM-025","解鎖BGM-026","解鎖BGM-027","解鎖BGM-028","解鎖BGM-029","解鎖BGM-030","解鎖BGM-031","解鎖BGM-032","解鎖BGM-033","解鎖BGM-034","解鎖BGM-035","解鎖BGM-036","解鎖BGM-037","解鎖BGM-038","解鎖BGM-039","解鎖BGM-040","解鎖BGM-041","解鎖BGM-042","解鎖BGM-043","解鎖BGM-044","解鎖BGM-045","解鎖BGM-046","解鎖BGM-047","解鎖BGM-048","解鎖BGM-049","解鎖BGM-050","解鎖BGM-051","解鎖BGM-052","解鎖BGM-053","解鎖BGM-054","解鎖BGM-055","解鎖BGM-056","解鎖BGM-057","解鎖BGM-058","解鎖BGM-059","解鎖BGM-060","解鎖BGM-061","解鎖BGM-062","解鎖BGM-063","解鎖BGM-064","解鎖BGM-065","解鎖BGM-066","解鎖BGM-067","解鎖BGM-068","解鎖BGM-069","解鎖BGM-070","解鎖BGM-071","解鎖BGM-072","解鎖BGM-073","解鎖BGM-074","解鎖BGM-075","解鎖BGM-076","解鎖BGM-077","解鎖BGM-078","解鎖BGM-079","解鎖BGM-080","解鎖BGM-081","解鎖BGM-082","解鎖BGM-083","解鎖BGM-084","解鎖BGM-085","解鎖BGM-086","解鎖BGM-087","解鎖BGM-088","解鎖BGM-089","解鎖BGM-090","解鎖BGM-091","解鎖BGM-092","解鎖BGM-093","解鎖BGM-094","解鎖BGM-095","解鎖BGM-096","解鎖BGM-097","解鎖BGM-098","解鎖BGM-099","解鎖BGM-100","解鎖BGM-101","解鎖BGM-102","解鎖BGM-103","解鎖BGM-104","解鎖BGM-105","解鎖BGM-106","解鎖BGM-107","解鎖BGM-108","解鎖BGM-109","解鎖BGM-110","解鎖BGM-111","解鎖BGM-112","解鎖BGM-113","解鎖BGM-114","解鎖BGM-115","解鎖BGM-116","解鎖BGM-117","解鎖BGM-118","解鎖BGM-119","解鎖BGM-120","解鎖BGM-121","解鎖BGM-122","解鎖BGM-123","解鎖BGM-124","解鎖BGM-125","解鎖BGM-126","解鎖BGM-127","解鎖BGM-128","解鎖BGM-129","解鎖BGM-130","解鎖BGM-131","解鎖BGM-132","解鎖BGM-133","解鎖BGM-134","解鎖BGM-135","解鎖BGM-136","解鎖BGM-137","解鎖BGM-138","解鎖BGM-139","解鎖BGM-140","解鎖BGM-141","解鎖BGM-142","解鎖BGM-143","解鎖BGM-144","解鎖BGM-145","解鎖BGM-146","解鎖BGM-147","解鎖BGM-148","解鎖BGM-149","解鎖BGM-150","解鎖BGM-151","解鎖BGM-152","解鎖BGM-153","解鎖BGM-154","解鎖BGM-155","解鎖BGM-156","解鎖BGM-157","解鎖BGM-158","解鎖BGM-159","解鎖BGM-160","解鎖BGM-161","解鎖BGM-162","解鎖BGM-163","解鎖BGM-164","解鎖BGM-165","解鎖BGM-166","解鎖BGM-167","解鎖BGM-168","解鎖BGM-169","解鎖BGM-170","解鎖BGM-171","解鎖BGM-172","解鎖BGM-173","解鎖BGM-174","解鎖BGM-175","解鎖BGM-176","解鎖BGM-177","解鎖BGM-178","解鎖BGM-179","解鎖BGM-180","解鎖BGM-181","解鎖BGM-182","解鎖BGM-183","解鎖BGM-184","解鎖BGM-185","解鎖BGM-186","解鎖BGM-187","解鎖BGM-188","解鎖BGM-189","解鎖BGM-190","解鎖BGM-191","解鎖BGM-192","解鎖BGM-193","解鎖BGM-194","解鎖BGM-195","解鎖BGM-196","解鎖BGM-197","解鎖BGM-198","解鎖BGM-199","解鎖BGM-200","","","","","","","","","","","","","","","","","","","","","","","","","","","","","","","","","","","","","","","","","","","","","","","","","","","","","","","","","","","","","","","","","","","","","","","","","","","","","","","","","","","","","","","","","","","","","","","","","","","",""],"terms":{"basic":["等級","LV","HP","HP","MP","MP","TP","TP","經驗值","EXP"],"commands":["戰鬥","高超走位","攻擊","防禦","物品","技能","裝備","狀態","隊伍順序","存檔","結束遊戲","設定","武器","護具","重要物品","變更","換上最強裝備","卸下所有裝備","新遊戲","繼續遊戲","新遊戲","回到標題","取消","","購入","售出","Sell"],"params":["HP 最大值","MP 最大值","攻擊力","防禦力","魔法攻擊","魔法防禦","速度","幸運值","命中率","迴避率"],"messages":{"actionFailure":"沒有命中%1！","actorDamage":"%1受到了%2點傷害！","actorDrain":"%1的%2被奪去了%3！","actorGain":"%1的%2增加了%3！","actorLoss":"%1的%2減少了%3！","actorNoDamage":"%1沒有受到任何傷害！","actorNoHit":"失誤！%1沒有受到任何傷害！","actorRecovery":"%1的%2恢複了%3！","alwaysDash":"始終衝刺","bgmVolume":"BGM音量","bgsVolume":"BGS音量","buffAdd":"%1的%2上升了！","buffRemove":"%1的%2還原了！","commandRemember":"記住命令","counterAttack":"%1的反擊！","criticalToActor":"痛恨一擊！！","criticalToEnemy":"會心一擊！！","debuffAdd":"%1的%2下降了！","defeat":"%1戰敗。","emerge":"%1粗乃玩惹。","enemyDamage":"%1受到了%2點傷害！","enemyDrain":"%1的%2被奪走了%3！","enemyGain":"%1的%2增加了%3！","enemyLoss":"%1的%2減少了%3！","enemyNoDamage":"%1沒有受到任何傷害！","enemyNoHit":"失誤！%1沒有受到任何傷害！","enemyRecovery":"%1的%2恢複了%3！","escapeFailure":"撤退失敗。","escapeStart":"%1準備撤退。","evasion":"%1躲開了攻擊！","expNext":"到下個%1","expTotal":"當前%1","file":"檔案","levelUp":"%1的%2上升了%3！","loadMessage":"讀取進度到?","magicEvasion":"%1抵消了魔法！","magicReflection":"%1反射了魔法！","meVolume":"ME音量","obtainExp":"獲得了%1點%2！","obtainGold":"獲得了%1\\G！","obtainItem":"%1被發現！","obtainSkill":"學會了%1！","partyName":"%1一行人","possession":"持有量","preemptive":"%1先馳得點。","saveMessage":"儲存進度到?","seVolume":"SE音量","substitute":"%1保護了%2！","surprise":"%1被偷襲。","useItem":"%1使用了%2！","victory":"%1勝利！"}},"testBattlers":[{"actorId":2,"equips":[161,0,0,47,73,203,204],"level":99},{"actorId":1,"equips":[159,1,2,3,4,201,250],"level":99},{"actorId":0,"equips":[1,1,2,3,4,201,250],"level":10},{"actorId":0,"equips":[1,1,2,3,4,201,250],"level":10}],"testTroopId":71,"title1Name":"ACastle","title2Name":"","titleBgm":{"name":"tukito_event_024","pan":0,"pitch":100,"volume":80},"variables":["","自由-大地圖位置","亞空城劇情","隨機亂數","主角X座標","主角Y座標","主角的方向","領隊角色","突破的空間數","區塊ID","萬用數字1","萬用數字2","萬用數字3","萬用數字4","觀看中的羈絆劇情","自宅BGM","罪惡","亞空城-NPC位置","夜劇情","持有魔法石","所在的房間","通關數","亞空-ST1上排水晶數","亞空-ST1下排水晶數","亞空-進入關卡編號","暫存自宅BGM","雜魚戰編號","拾取的藥草種類","家具用主角X座標","家具用主角Y座標","資料庫-選項","資料庫-調查項目","地圖ID","亞空-ST2上排水晶數","亞空-ST2下排水晶數","探險隊-基礎報酬數量","探險隊-需求回合","探險隊-稀有報酬獲得率","家具用萬用數字1","家具用萬用數字2","探險隊-稀有報酬數量","目標1 X","目標1 Y","目標2 X","目標2 Y","目標3 X","目標3 Y","目標4 X","目標4 Y","目標5 X","目標5 Y","目標6 X","目標6 Y","目標7 X","目標7 Y","目標8 X","目標8 Y","目標9 X","目標9 Y","目標10 X","目標10 Y","探險隊-隊伍屬性","家具用萬用數字3","探險隊-探險屬性","要增加的羈絆度","亞空-ST3上排水晶數","亞空-ST3下排水晶數","雷擊等 等待幀數","防衛戰敵人擊破數","暫存傢具編號","正在編輯的傢具編號","目標1 區塊ID","目標2 區塊ID","目標3 區塊ID","目標4 區塊ID","目標5 區塊ID","目標6 區塊ID","目標7 區塊ID","目標8 區塊ID","目標9 區塊ID","目標10 區塊ID","目標11 X","目標11 Y","目標12 X","目標12 Y","目標13 X","目標13 Y","目標14 X","目標14 Y","目標15 X","目標15 Y","目標16 X","目標16 Y","目標17 X","目標17 Y","目標18 X","目標18 Y","目標19 X","目標19 Y","目標20 X","目標20 Y","快速編成1-1","快速編成1-2","快速編成1-3","快速編成1-4","快速編成1-5","快速編成1-6","快速編成2-1","快速編成2-2","快速編成2-3","快速編成2-4","快速編成2-5","快速編成2-6","快速編成3-1","快速編成3-2","快速編成3-3","快速編成3-4","快速編成3-5","快速編成3-6","快速編成4-1","快速編成4-2","快速編成4-3","快速編成4-4","快速編成4-5","快速編成4-6","快速編成5-1","快速編成5-2","快速編成5-3","快速編成5-4","快速編成5-5","快速編成5-6","快速編成暫存1","快速編成暫存2","快速編成暫存3","快速編成暫存4","快速編成暫存5","快速編成暫存6","當前隊伍1","當前隊伍2","當前隊伍3","當前隊伍4","當前隊伍5","當前隊伍6","探險地點1","探險地點2","探險地點3","探險地點4","探險地點5","探險隊1-任務剩餘回合","探險隊2-任務剩餘回合","探險隊3-任務剩餘回合","探險隊4-任務剩餘回合","探險隊5-任務剩餘回合","探險-派遣隊伍1","探險-派遣隊伍2","探險-派遣隊伍3","探險-派遣隊伍4","探險-派遣隊伍5","離房用暫存隊伍1","離房用暫存隊伍2","離房用暫存隊伍3","離房用暫存隊伍4","離房用暫存隊伍5","離房用暫存隊伍6","自由-目的地","自由-顯示地圖名稱","ST3 房間密碼和","亞空-ST4上排水晶數","亞空-ST4下排水晶數","自由-奇黎村劇情","自宅BGM 音調","SRPG 剩餘玩家角色數量","SRPG 剩餘敵人數量","SRPG 回合數","SRPG 行動事件ID","SRPG 目標事件ID","自宅BGM 暫存音調","亞空-ST5上排水晶數","亞空-ST5下排水晶數","出發外傳編號","亞空-ST6上排水晶數","亞空-ST6下排水晶數","亞空-樓梯數量","亞空-ST7上排水晶數","亞空-ST7下排水晶數","ST7 隊伍1成員1","ST7 隊伍1成員2","ST7 隊伍1成員3","ST7 隊伍2成員1","ST7 隊伍2成員2","ST7 隊伍2成員3","ST7 操作中隊伍","STR 對話次數","STR 殺害人形","STR 突破關數","STR 解決問題數","ST4 風向","ST5 看花次數","訓練戰鬥BGM","訓練戰鬥BGM音調","","傢俱1種類","傢俱2種類","傢俱3種類","傢俱4種類","傢俱5種類","傢俱6種類","傢俱7種類","傢俱8種類","傢俱9種類","傢俱10種類","傢俱11種類","傢俱12種類","傢俱13種類","傢俱14種類","傢俱15種類","傢俱16種類","傢俱17種類","傢俱18種類","傢俱19種類","傢俱20種類","傢俱1X座標","傢俱2X座標","傢俱3X座標","傢俱4X座標","傢俱5X座標","傢俱6X座標","傢俱7X座標","傢俱8X座標","傢俱9X座標","傢俱10X座標","傢俱11X座標","傢俱12X座標","傢俱13X座標","傢俱14X座標","傢俱15X座標","傢俱16X座標","傢俱17X座標","傢俱18X座標","傢俱19X座標","傢俱20X座標","傢俱1Y座標","傢俱2Y座標","傢俱3Y座標","傢俱4Y座標","傢俱5Y座標","傢俱6Y座標","傢俱7Y座標","傢俱8Y座標","傢俱9Y座標","傢俱10Y座標","傢俱11Y座標","傢俱12Y座標","傢俱13Y座標","傢俱14Y座標","傢俱15Y座標","傢俱16Y座標","傢俱17Y座標","傢俱18Y座標","傢俱19Y座標","傢俱20Y座標","羈絆度 主角-利歐","羈絆度 主角-大中天","羈絆度 主角-苦力喵","羈絆度 主角-國泰","羈絆度 主角-修伊","羈絆度 主角-愛莉絲","羈絆度 利歐-大中天","羈絆度 利歐-苦力喵","羈絆度 利歐-國泰","羈絆度 利歐-修伊","羈絆度 利歐-愛莉絲","羈絆度 大中天-苦力喵","羈絆度 大中天-國泰","羈絆度 大中天-修伊","羈絆度 大中天-愛莉絲","羈絆度 苦力喵-國泰","羈絆度 苦力喵-修伊","羈絆度 苦力喵-愛莉絲","羈絆度 國泰-修伊","羈絆度 國泰-愛莉絲","羈絆度 修伊-愛莉絲","羈絆度 主角-雷歐","羈絆度 利歐-雷歐","羈絆度 大中天-雷歐","羈絆度 苦力喵-雷歐","羈絆度 國泰-雷歐","羈絆度 修伊-雷歐","羈絆度 愛莉絲-雷歐","羈絆度 主角-狩矢","羈絆度 利歐-狩矢","羈絆度 大中天-狩矢","羈絆度 苦力喵-狩矢","羈絆度 國泰-狩矢","羈絆度 修伊-狩矢","羈絆度 愛莉絲-狩矢","羈絆度 雷歐-狩矢","羈絆度 主角-利優","羈絆度 利歐-利優","羈絆度 大中天-利優","羈絆度 苦力喵-利優","羈絆度 國泰-利優","羈絆度 修伊-利優","羈絆度 愛莉絲-利優","羈絆度 雷歐-利優","羈絆度 狩矢-利優","羈絆度 主角-洛伊","羈絆度 利歐-洛伊","羈絆度 大中天-洛伊","羈絆度 苦力喵-洛伊","羈絆度 國泰-洛伊","羈絆度 修伊-洛伊","羈絆度 愛莉絲-洛伊","羈絆度 雷歐-洛伊","羈絆度 狩矢-洛伊","羈絆度 利優-洛伊","羈絆度 主角-望","羈絆度 利歐-望","羈絆度 大中天-望","羈絆度 苦力喵-望","羈絆度 國泰-望","羈絆度 修伊-望","羈絆度 愛莉絲-望","羈絆度 雷歐-望","羈絆度 狩矢-望","羈絆度 利優-望","羈絆度 洛伊-望","羈絆度 主角-斯利茲","羈絆度 利歐-斯利茲","羈絆度 大中天-斯利茲","羈絆度 苦力喵-斯利茲","羈絆度 國泰-斯利茲","羈絆度 修伊-斯利茲","羈絆度 愛莉絲-斯利茲","羈絆度 雷歐-斯利茲","羈絆度 狩矢-斯利茲","羈絆度 利優-斯利茲","羈絆度 洛伊-斯利茲","羈絆度 望-斯利茲","羈絆度 主角-殘楓","羈絆度 利歐-殘楓","羈絆度 大中天-殘楓","羈絆度 苦力喵-殘楓","羈絆度 國泰-殘楓","羈絆度 修伊-殘楓","羈絆度 愛莉絲-殘楓","羈絆度 雷歐-殘楓","羈絆度 狩矢-殘楓","羈絆度 利優-殘楓","羈絆度 洛伊-殘楓","羈絆度 望-殘楓","羈絆度 斯利茲-殘楓","羈絆度 主角-祈","羈絆度 利歐-祈","羈絆度 大中天-祈","羈絆度 苦力喵-祈","羈絆度 國泰-祈","羈絆度 修伊-祈","羈絆度 愛莉絲-祈","羈絆度 雷歐-祈","羈絆度 狩矢-祈","羈絆度 利優-祈","羈絆度 洛伊-祈","羈絆度 望-祈","羈絆度 斯利茲-祈","羈絆度 殘楓-祈","羈絆度 主角-利牙","羈絆度 利歐-利牙","羈絆度 大中天-利牙","羈絆度 苦力喵-利牙","羈絆度 國泰-利牙","羈絆度 修伊-利牙","羈絆度 愛莉絲-利牙","羈絆度 雷歐-利牙","羈絆度 狩矢-利牙","羈絆度 利優-利牙","羈絆度 洛伊-利牙","羈絆度 望-利牙","羈絆度 斯利茲-利牙","羈絆度 殘楓-利牙","羈絆度 祈-利牙","","","","","","","","","","","","","","","","","","","","","","","","","","","","","","","","","","","","","","","","","","","","","","","","","","","","","","","","","","","","","","","","","","","","","","","","","","","","","","","","","","","","","","","","","","","","","","","","","","","","","","","","","","","","","","","","","","","","","","","","","","","","","","","","","","","","","","","","","","","","","","","","","","","","","","","","","","","","","","","","","","","","","","","","","","","","","","","","","","","","","","","","","","","","","","","","","","","","","","","","","","","","","","","","","","","","","","","","","","","","","","","","","","","","","","","","","","","","","","","","","","","","","","","","","","","","","","","","","","","","","","","","","","","","","","","","","","","","","","","","","","","","","","","","","","","","","","","","","","","","","","","","","","","","","","","","","","","","","","","","","","","","","","","","","","","","","","","","","","","","","","","","","","","","","","","","","","","","","","","","","","","","","","","","","","","","","","","","","","","","羈絆 末","","","","","","","","","","","","","","","","","","","","","","","","","","","","","","","","","","","","","","","","","","","","","","","","","","","","","","","","","","","","","","","","","","","","","","","","","","","","","","","","","","","","","","","","","","","","","","","","","","","","","","","","","","","","","","","","","","","","","","","","","","","","","","","","","","","","","","","","","","","","","連絡站郵件進度1","連絡站郵件進度2","連絡站郵件進度3","連絡站郵件進度4","連絡站郵件進度5","連絡站郵件進度6","連絡站郵件進度7","連絡站郵件進度8","連絡站郵件進度9","連絡站郵件進度10","連絡站郵件進度11","連絡站郵件進度12","連絡站郵件進度13","連絡站郵件進度14","連絡站郵件進度15","連絡站郵件進度16","連絡站郵件進度17","連絡站郵件進度18","連絡站郵件進度19","連絡站郵件進度20","連絡站郵件進度21","連絡站郵件進度22","連絡站郵件進度23","連絡站郵件進度24","連絡站郵件進度25","連絡站郵件進度26","連絡站郵件進度27","連絡站郵件進度28","連絡站郵件進度29","連絡站郵件進度30","連絡站郵件進度31","連絡站郵件進度32","連絡站郵件進度33","連絡站郵件進度34","連絡站郵件進度35","連絡站郵件進度36","連絡站郵件進度37","連絡站郵件進度38","連絡站郵件進度39","連絡站郵件進度40","連絡站郵件進度41","連絡站郵件進度42","連絡站郵件進度43","連絡站郵件進度44","連絡站郵件進度45","連絡站郵件進度46","連絡站郵件進度47","連絡站郵件進度48","連絡站郵件進度49","連絡站郵件進度50","同伴疑難進度1","同伴疑難進度2","同伴疑難進度3","同伴疑難進度4","同伴疑難進度5","同伴疑難進度6","同伴疑難進度7","同伴疑難進度8","同伴疑難進度9","同伴疑難進度10","同伴疑難進度11","同伴疑難進度12","同伴疑難進度13","同伴疑難進度14","同伴疑難進度15","同伴疑難進度16","同伴疑難進度17","同伴疑難進度18","同伴疑難進度19","同伴疑難進度20","同伴疑難進度21","同伴疑難進度22","同伴疑難進度23","同伴疑難進度24","同伴疑難進度25","同伴疑難進度26","同伴疑難進度27","同伴疑難進度28","同伴疑難進度29","同伴疑難進度30","同伴疑難進度31","同伴疑難進度32","同伴疑難進度33","同伴疑難進度34","同伴疑難進度35","同伴疑難進度36","同伴疑難進度37","同伴疑難進度38","同伴疑難進度39","同伴疑難進度40","同伴疑難進度41","同伴疑難進度42","同伴疑難進度43","同伴疑難進度44","同伴疑難進度45","同伴疑難進度46","同伴疑難進度47","同伴疑難進度48","同伴疑難進度49","同伴疑難進度50"],"versionId":32432020,"victoryMe":{"name":"Victory1","pan":0,"pitch":100,"volume":100},"weaponTypes":["","斧","槍","劍","杖","刀","弓","工具","特殊","主角專用","大中天專用","苦力喵專用","國泰專用","雷歐專用","書","利優專用","創也專用","","","",""],"windowTone":[-51,0,68,0],"battleback1Name":"Dirt1","battleback2Name":"Sky"}